urlkit/__init__.py
urlkit/http/__init__.py
urlkit/http/http_path.py
urlkit/http/http_queries.py
urlkit/http/http_url.py
urlkit/url.py
urlkit-0.2.2.dist-info/LICENSE
urlkit-0.2.2.dist-info/METADATA
urlkit-0.2.2.dist-info/WHEEL
urlkit-0.2.2.dist-info/RECORD
