Metadata-Version: 2.1
Name: urlkit
Version: 0.2.2
Summary: Working with URLs using urllib is a bit of a pain. urlkit makes everything much easier.
License: MIT
Author: Dale Myers
Author-email: dale@myers.io
Requires-Python: >=3.9,<4.0
Classifier: License :: OSI Approved :: MIT License
Classifier: Programming Language :: Python :: 3
Classifier: Programming Language :: Python :: 3.9
Classifier: Programming Language :: Python :: 3.10
Classifier: Programming Language :: Python :: 3.11
Classifier: Programming Language :: Python :: 3.12
